yarnspawner/__init__.py
yarnspawner/_version.py
yarnspawner/apihandler.py
yarnspawner/jupyter_labhub.py
yarnspawner/singleuser.py
yarnspawner/spawner.py
jupyterhub_yarnspawner-0.4.0.dist-info/LICENSE
jupyterhub_yarnspawner-0.4.0.dist-info/METADATA
jupyterhub_yarnspawner-0.4.0.dist-info/WHEEL
jupyterhub_yarnspawner-0.4.0.dist-info/top_level.txt
jupyterhub_yarnspawner-0.4.0.dist-info/RECORD
